heisskleber/__init__.py
heisskleber/py.typed
heisskleber/console/__init__.py
heisskleber/console/config.py
heisskleber/console/receiver.py
heisskleber/console/sender.py
heisskleber/core/__init__.py
heisskleber/core/config.py
heisskleber/core/packer.py
heisskleber/core/receiver.py
heisskleber/core/sender.py
heisskleber/core/unpacker.py
heisskleber/core/utils.py
heisskleber/file/__init__.py
heisskleber/file/config.py
heisskleber/file/receiver.py
heisskleber/file/sender.py
heisskleber/mqtt/__init__.py
heisskleber/mqtt/config.py
heisskleber/mqtt/receiver.py
heisskleber/mqtt/sender.py
heisskleber/serial/__init__.py
heisskleber/serial/config.py
heisskleber/serial/receiver.py
heisskleber/serial/sender.py
heisskleber/tcp/__init__.py
heisskleber/tcp/config.py
heisskleber/tcp/receiver.py
heisskleber/tcp/sender.py
heisskleber/udp/__init__.py
heisskleber/udp/config.py
heisskleber/udp/receiver.py
heisskleber/udp/sender.py
heisskleber/zmq/__init__.py
heisskleber/zmq/config.py
heisskleber/zmq/receiver.py
heisskleber/zmq/sender.py
heisskleber-1.2.1.dist-info/METADATA
heisskleber-1.2.1.dist-info/WHEEL
heisskleber-1.2.1.dist-info/licenses/LICENSE
heisskleber-1.2.1.dist-info/RECORD
