Metadata-Version: 2.4
Name: heisskleber
Version: 1.2.1
Summary: Heisskleber
Project-URL: Homepage, https://github.com/flucto-gmbh/heisskleber
Project-URL: Repository, https://github.com/flucto-gmbh/heisskleber
Project-URL: Documentation, https://heisskleber.readthedocs.io
Author-email: Felix Weiler-Detjen <felix@flucto.tech>
License: MIT License
License-File: LICENSE
Requires-Python: >=3.10
Requires-Dist: aiomqtt>=2.3.0
Requires-Dist: pyserial>=3.5
Requires-Dist: pyyaml>=6.0.2
Requires-Dist: pyzmq>=26.2.0
Requires-Dist: watchfiles>=0.24.0
Provides-Extra: docs
Requires-Dist: furo>=2024.8.6; extra == 'docs'
Requires-Dist: myst-parser>=4.0.0; extra == 'docs'
Requires-Dist: sphinx-autobuild>=2024.9.19; extra == 'docs'
Requires-Dist: sphinx-autodoc-typehints; extra == 'docs'
Requires-Dist: sphinx-copybutton; extra == 'docs'
Requires-Dist: sphinx-rtd-theme>=0.5.1; extra == 'docs'
Requires-Dist: sphinx>=8.0.2; extra == 'docs'
Provides-Extra: test
Requires-Dist: coverage[toml]>=7.6.1; extra == 'test'
Requires-Dist: freezegun>=1.5.1; extra == 'test'
Requires-Dist: pytest-asyncio>=0.24.0; extra == 'test'
Requires-Dist: pytest-cov>=5.0.0; extra == 'test'
Requires-Dist: pytest>=8.3.3; extra == 'test'
Requires-Dist: xdoctest>=1.2.0; extra == 'test'
